roman/__init__.py
roman/cli.py
roman/roman.py
romanpy-1.3.2.dist-info/licenses/LICENSE
romanpy-1.3.2.dist-info/METADATA
romanpy-1.3.2.dist-info/WHEEL
romanpy-1.3.2.dist-info/entry_points.txt
romanpy-1.3.2.dist-info/top_level.txt
romanpy-1.3.2.dist-info/RECORD
