Metadata-Version: 2.4
Name: RomanPy
Version: 1.3.2
Summary: Effortlessly convert decimal numbers to Roman numerals in Python.
Author-email: "M.P. van de Weerd" <michael@parcifal.dev>
License-Expression: AGPL-3.0-only
Project-URL: Homepage, https://gitlab.com/parcifal/roman-py
Project-URL: Bug Tracker, https://gitlab.com/parcifal/roman-py/-/issues
Keywords: unicode,decimal numbers,roman numbers,conversion,numeral system
Classifier: Development Status :: 5 - Production/Stable
Classifier: Intended Audience :: Developers
License-File: LICENSE
Requires-Dist: tomli
Provides-Extra: dev
Requires-Dist: pylint; extra == "dev"
Requires-Dist: pylint-gitlab; extra == "dev"
Requires-Dist: pytest; extra == "dev"
Requires-Dist: pytest-cov; extra == "dev"
Requires-Dist: coverage; extra == "dev"
Dynamic: license-file
